cnc_api_client_core-1.4.1.data/purelib/cnc_api_client_core/__init__.py
cnc_api_client_core-1.4.1.data/purelib/cnc_api_client_core/__version__.py
cnc_api_client_core-1.4.1.data/purelib/cnc_api_client_core/Win64/cnc_api_client_core.pyd
cnc_api_client_core-1.4.1.dist-info/LICENSE.md
cnc_api_client_core-1.4.1.dist-info/METADATA
cnc_api_client_core-1.4.1.dist-info/WHEEL
cnc_api_client_core-1.4.1.dist-info/top_level.txt
cnc_api_client_core-1.4.1.dist-info/RECORD
