Metadata-Version: 2.1
Name: cnc-api-client-core
Version: 1.4.1
Summary: CNC API Client Core for Python
Home-page: https://github.com/rosettacnc-classroom/cnc_api_client_core_1/
Author: RosettaCNC
Author-email: support@rosettacnc.com
License: Other/Proprietary License
Project-URL: Documentation, http://wiki.rosettacnc.com/en/software/rosettacnccncapiclientcore
Classifier: Intended Audience :: Developers
Classifier: Topic :: Software Development
Classifier: License :: Other/Proprietary License
Classifier: Programming Language :: Python :: 3.9
Classifier: Programming Language :: Python :: 3.10
Classifier: Programming Language :: Python :: 3.11
Classifier: Operating System :: Microsoft :: Windows
Requires-Python: >=3.9,<=3.11
License-File: LICENSE.md
